{
  "EDITOR_STATE": {
    "allProjectFiles": {
      "1d1d3824-a5d6-4bcc-8324-3672342dc9a7": {
        "id": "1d1d3824-a5d6-4bcc-8324-3672342dc9a7",
        "parent": null,
        "name": "kkkkkk",
        "type": "DIRECTORY",
        "isDirectory": true,
        "children": [
          "7139d284-d592-4aba-915e-0c5a0d7c07f9"
        ],
        "isRemovable": false,
        "filePath": "kkkkkk"
      },
      "7139d284-d592-4aba-915e-0c5a0d7c07f9": {
        "id": "7139d284-d592-4aba-915e-0c5a0d7c07f9",
        "parent": "1d1d3824-a5d6-4bcc-8324-3672342dc9a7",
        "name": "lambda.js",
        "type": "JS_LAMBDA",
        "isDirectory": false,
        "children": [],
        "isRemovable": true,
        "filePath": "kkkkkk/lambda.js",
        "code": "exports.handler = function(event, context, callback) {\n    \n    callback(null, {\"message\": \"Successfully executed\"});\n}",
        "config": {
          "runtime": "nodejs8.10",
          "handler": "handler",
          "timeout": 60,
          "memory": 128,
          "layers": []
        },
        "triggers": []
      }
    },
    "deletedFiles": [],
    "rootNode": "1d1d3824-a5d6-4bcc-8324-3672342dc9a7",
    "openFiles": [
      "7139d284-d592-4aba-915e-0c5a0d7c07f9"
    ],
    "currentFileId": "7139d284-d592-4aba-915e-0c5a0d7c07f9",
    "resources": {},
    "customTemplate": {
      "dialect": null,
      "definitions": {}
    },
    "envVariables": [
      {
        "lambdaId": "all",
        "varKey": "SIGMA_AWS_ACC_ID",
        "varValue": null,
        "shouldPersist": false,
        "displayOnly": false,
        "editable": false
      }
    ],
    "packageJSON": {
      "dependencies": {}
    }
  },
  "PROJECT_META": {
    "projectName": "kkkkkk",
    "projectDescription": "",
    "projectVersion": "1.0.0",
    "projectRegion": "us-east-1",
    "platform": "AWS",
    "platformRegions": {},
    "lastSave": 1565697311005
  },
  "VCS_STATE": {
    "provider": "GitHub",
    "repo": {
      "name": "kkkkkk",
      "url": "https://github.com/Kumudikatest/kkkkkk"
    }
  }
}